code2prompt_rs-3.2.1.dist-info/METADATA
code2prompt_rs-3.2.1.dist-info/WHEEL
code2prompt_rs/code2prompt.py
code2prompt_rs/__init__.py
code2prompt_rs/code2prompt_rs.abi3.so
code2prompt_rs-3.2.1.dist-info/RECORD
