Metadata-Version: 2.4
Name: code2prompt_rs
Version: 3.2.1
Classifier: Development Status :: 5 - Production/Stable
Classifier: Intended Audience :: Developers
Classifier: License :: OSI Approved :: MIT License
Classifier: Programming Language :: Python :: 3
Classifier: Programming Language :: Python :: 3 :: Only
Classifier: Programming Language :: Python :: 3.11
Classifier: Programming Language :: Python :: 3.12
Classifier: Programming Language :: Rust
Classifier: Topic :: Software Development :: Libraries :: Python Modules
Requires-Dist: pip>=25.0.1
Requires-Dist: patchelf>=0.17.2.1
Summary: Python bindings for code2prompt
Author-email: Olivier D'Ancona <olivier.dancona@master.hes-so.ch>, Mufeed VH <contact@mufeedvh.com>
Requires-Python: >=3.11
Project-URL: Homepage, https://code2prompt.dev
Project-URL: Documentation, https://code2prompt.dev/docs/welcome
Project-URL: Repository, https://github.com/mufeedvh/code2prompt
